{
  "annotations": {
    "changelogDate": "20250817181209"
  },
  "applications": ["*"],
  "dto": "mapstruct",
  "fields": [
    {
      "fieldName": "orderDate",
      "fieldType": "Instant",
      "fieldValidateRules": ["required"]
    },
    {
      "fieldName": "status",
      "fieldType": "OrderStatus",
      "fieldValidateRules": ["required"],
      "fieldValues": "PENDING,CONFIRMED,REJECTED,PICKED_UP,IN_TRANSIT,DELIVERED,CANCELLED"
    },
    {
      "fieldName": "totalAmount",
      "fieldType": "BigDecimal",
      "fieldValidateRules": ["required"]
    },
    {
      "fieldName": "deliveryAddress",
      "fieldType": "String",
      "fieldValidateRules": ["required"]
    },
    {
      "fieldName": "notes",
      "fieldType": "String"
    }
  ],
  "name": "PurchaseOrder",
  "pagination": "pagination",
  "relationships": [
    {
      "otherEntityField": "login",
      "otherEntityName": "user",
      "relationshipName": "buyer",
      "relationshipSide": "left",
      "relationshipType": "many-to-one",
      "relationshipWithBuiltInEntity": true
    }
  ],
  "service": "serviceImpl"
}
